{
    "images": [
        {
            "width": 2048,
            "height": 2048,
            "id": 1,
            "file_name": "PP_044_9.jpg"
        }
    ],
    "categories": [
        {
            "id": 1,
            "name": "pet"
        },
        {
            "id": 2,
            "name": "ps"
        },
        {
            "id": 3,
            "name": "pp"
        },
        {
            "id": 4,
            "name": "pe"
        }
    ],
    "annotations": [
        {
            "id": 1,
            "image_id": 1,
            "category_id": 3,
            "metainfo_id": 44,
            "segmentation": [
                [
                    905,
                    704,
                    887,
                    705,
                    869,
                    708,
                    851,
                    712,
                    833,
                    717,
                    815,
                    724,
                    797,
                    732,
                    779,
                    743,
                    761,
                    756,
                    744,
                    772,
                    728,
                    787,
                    714,
                    805,
                    703,
                    823,
                    693,
                    841,
                    685,
                    859,
                    678,
                    877,
                    673,
                    895,
                    671,
                    913,
                    670,
                    931,
                    670,
                    949,
                    671,
                    967,
                    673,
                    985,
                    678,
                    1003,
                    683,
                    1021,
                    690,
                    1039,
                    699,
                    1057,
                    709,
                    1075,
                    723,
                    1093,
                    738,
                    1111,
                    756,
                    1126,
                    774,
                    1141,
                    792,
                    1153,
                    810,
                    1162,
                    828,
                    1170,
                    846,
                    1176,
                    864,
                    1181,
                    882,
                    1184,
                    900,
                    1192,
                    913,
                    1210,
                    930,
                    1225,
                    948,
                    1229,
                    966,
                    1224,
                    983,
                    1209,
                    991,
                    1191,
                    999,
                    1173,
                    1017,
                    1162,
                    1035,
                    1153,
                    1053,
                    1141,
                    1071,
                    1126,
                    1089,
                    1109,
                    1105,
                    1091,
                    1117,
                    1073,
                    1127,
                    1055,
                    1135,
                    1037,
                    1141,
                    1019,
                    1146,
                    1001,
                    1149,
                    983,
                    1150,
                    965,
                    1152,
                    947,
                    1151,
                    929,
                    1149,
                    911,
                    1145,
                    893,
                    1140,
                    875,
                    1134,
                    857,
                    1125,
                    839,
                    1115,
                    821,
                    1103,
                    803,
                    1088,
                    785,
                    1072,
                    768,
                    1054,
                    752,
                    1036,
                    741,
                    1018,
                    731,
                    1000,
                    723,
                    982,
                    717,
                    964,
                    711,
                    946,
                    707,
                    928,
                    705,
                    910,
                    704
                ]
            ],
            "bbox": [
                670,
                704,
                482,
                525
            ],
            "ignore": 0,
            "iscrowd": 0,
            "area": 185107.0
        },
        {
            "id": 2,
            "image_id": 1,
            "category_id": 3,
            "metainfo_id": 44,
            "segmentation": [
                [
                    406,
                    1039,
                    386,
                    1063,
                    368,
                    1085,
                    343,
                    1089,
                    318,
                    1094,
                    293,
                    1101,
                    268,
                    1109,
                    243,
                    1120,
                    218,
                    1133,
                    193,
                    1150,
                    168,
                    1170,
                    144,
                    1194,
                    125,
                    1219,
                    109,
                    1244,
                    95,
                    1269,
                    86,
                    1294,
                    78,
                    1319,
                    72,
                    1344,
                    69,
                    1369,
                    66,
                    1394,
                    67,
                    1419,
                    69,
                    1444,
                    74,
                    1469,
                    81,
                    1494,
                    89,
                    1519,
                    100,
                    1544,
                    113,
                    1569,
                    129,
                    1594,
                    149,
                    1619,
                    171,
                    1643,
                    196,
                    1666,
                    221,
                    1684,
                    246,
                    1700,
                    271,
                    1712,
                    296,
                    1722,
                    320,
                    1731,
                    345,
                    1731,
                    370,
                    1731,
                    395,
                    1731,
                    420,
                    1731,
                    445,
                    1731,
                    470,
                    1731,
                    495,
                    1731,
                    520,
                    1723,
                    545,
                    1712,
                    570,
                    1700,
                    595,
                    1683,
                    620,
                    1662,
                    643,
                    1639,
                    665,
                    1614,
                    682,
                    1589,
                    695,
                    1564,
                    706,
                    1539,
                    715,
                    1514,
                    720,
                    1489,
                    724,
                    1464,
                    725,
                    1439,
                    725,
                    1414,
                    723,
                    1389,
                    719,
                    1364,
                    713,
                    1339,
                    703,
                    1314,
                    691,
                    1289,
                    677,
                    1264,
                    660,
                    1239,
                    642,
                    1214,
                    620,
                    1189,
                    596,
                    1167,
                    572,
                    1147,
                    547,
                    1131,
                    522,
                    1116,
                    511,
                    1091,
                    499,
                    1066,
                    474,
                    1047,
                    449,
                    1040,
                    424,
                    1039
                ]
            ],
            "bbox": [
                66,
                1039,
                659,
                692
            ],
            "ignore": 0,
            "iscrowd": 0,
            "area": 341797.5
        },
        {
            "id": 3,
            "image_id": 1,
            "category_id": 3,
            "metainfo_id": 44,
            "segmentation": [
                [
                    1498,
                    1157,
                    1474,
                    1158,
                    1450,
                    1160,
                    1426,
                    1164,
                    1402,
                    1171,
                    1378,
                    1180,
                    1354,
                    1189,
                    1330,
                    1201,
                    1306,
                    1214,
                    1282,
                    1230,
                    1258,
                    1250,
                    1235,
                    1272,
                    1215,
                    1295,
                    1198,
                    1319,
                    1184,
                    1343,
                    1174,
                    1367,
                    1165,
                    1391,
                    1158,
                    1415,
                    1151,
                    1439,
                    1151,
                    1463,
                    1151,
                    1487,
                    1151,
                    1511,
                    1157,
                    1535,
                    1163,
                    1559,
                    1169,
                    1583,
                    1178,
                    1607,
                    1190,
                    1631,
                    1205,
                    1655,
                    1224,
                    1679,
                    1247,
                    1701,
                    1271,
                    1719,
                    1295,
                    1734,
                    1319,
                    1746,
                    1343,
                    1756,
                    1367,
                    1765,
                    1391,
                    1771,
                    1415,
                    1776,
                    1439,
                    1779,
                    1463,
                    1780,
                    1487,
                    1780,
                    1511,
                    1778,
                    1535,
                    1773,
                    1559,
                    1769,
                    1583,
                    1761,
                    1607,
                    1752,
                    1631,
                    1739,
                    1655,
                    1720,
                    1679,
                    1703,
                    1703,
                    1681,
                    1724,
                    1658,
                    1743,
                    1634,
                    1762,
                    1610,
                    1773,
                    1586,
                    1783,
                    1562,
                    1791,
                    1538,
                    1797,
                    1514,
                    1802,
                    1490,
                    1802,
                    1466,
                    1802,
                    1442,
                    1802,
                    1418,
                    1799,
                    1395,
                    1794,
                    1371,
                    1787,
                    1347,
                    1775,
                    1323,
                    1760,
                    1299,
                    1744,
                    1275,
                    1724,
                    1251,
                    1700,
                    1229,
                    1676,
                    1212,
                    1652,
                    1198,
                    1628,
                    1186,
                    1604,
                    1176,
                    1580,
                    1168,
                    1556,
                    1162,
                    1532,
                    1159,
                    1508,
                    1158
                ]
            ],
            "bbox": [
                1151,
                1157,
                651,
                623
            ],
            "ignore": 0,
            "iscrowd": 0,
            "area": 318744.0
        }
    ],
    "info": {
        "year": 2021,
        "version": "1.0",
        "contributor": "datamaker"
    },
    "metainfo": [
        {
            "id": 1,
            "name": "pet_식품용기류_투명_병류_대_비압축_라벨유",
            "category_id": 1,
            "container": true,
            "transparent": true,
            "shape": 0,
            "size": 0,
            "compress": 0,
            "label": true
        },
        {
            "id": 2,
            "name": "pet_식품용기류_투명_병류_대_비압축_라벨무",
            "category_id": 1,
            "container": true,
            "transparent": true,
            "shape": 0,
            "size": 0,
            "compress": 0,
            "label": false
        },
        {
            "id": 3,
            "name": "pet_식품용기류_투명_병류_대_수평압축_라벨유",
            "category_id": 1,
            "container": true,
            "transparent": true,
            "shape": 0,
            "size": 0,
            "compress": 1,
            "label": true
        },
        {
            "id": 4,
            "name": "pet_식품용기류_투명_병류_대_수평압축_라벨무",
            "category_id": 1,
            "container": true,
            "transparent": true,
            "shape": 0,
            "size": 0,
            "compress": 1,
            "label": false
        },
        {
            "id": 5,
            "name": "pet_식품용기류_투명_병류_대_수직압축_라벨유",
            "category_id": 1,
            "container": true,
            "transparent": true,
            "shape": 0,
            "size": 0,
            "compress": 2,
            "label": true
        },
        {
            "id": 6,
            "name": "pet_식품용기류_투명_병류_대_수직압축_라벨무",
            "category_id": 1,
            "container": true,
            "transparent": true,
            "shape": 0,
            "size": 0,
            "compress": 2,
            "label": false
        },
        {
            "id": 7,
            "name": "pet_식품용기류_투명_병류_소_비압축_라벨유",
            "category_id": 1,
            "container": true,
            "transparent": true,
            "shape": 0,
            "size": 1,
            "compress": 0,
            "label": true
        },
        {
            "id": 8,
            "name": "pet_식품용기류_투명_병류_소_비압축_라벨무",
            "category_id": 1,
            "container": true,
            "transparent": true,
            "shape": 0,
            "size": 1,
            "compress": 0,
            "label": false
        },
        {
            "id": 9,
            "name": "pet_식품용기류_투명_병류_소_수평압축_라벨유",
            "category_id": 1,
            "container": true,
            "transparent": true,
            "shape": 0,
            "size": 1,
            "compress": 1,
            "label": true
        },
        {
            "id": 10,
            "name": "pet_식품용기류_투명_병류_소_수평압축_라벨무",
            "category_id": 1,
            "container": true,
            "transparent": true,
            "shape": 0,
            "size": 1,
            "compress": 1,
            "label": false
        },
        {
            "id": 11,
            "name": "pet_식품용기류_투명_병류_소_수직압축_라벨유",
            "category_id": 1,
            "container": true,
            "transparent": true,
            "shape": 0,
            "size": 1,
            "compress": 2,
            "label": true
        },
        {
            "id": 12,
            "name": "pet_식품용기류_투명_병류_소_수직압축_라벨무",
            "category_id": 1,
            "container": true,
            "transparent": true,
            "shape": 0,
            "size": 1,
            "compress": 2,
            "label": false
        },
        {
            "id": 13,
            "name": "pet_식품용기류_불투명_병류_대_비압축_라벨유",
            "category_id": 1,
            "container": true,
            "transparent": false,
            "shape": 0,
            "size": 0,
            "compress": 0,
            "label": true
        },
        {
            "id": 14,
            "name": "pet_식품용기류_불투명_병류_대_비압축_라벨무",
            "category_id": 1,
            "container": true,
            "transparent": false,
            "shape": 0,
            "size": 0,
            "compress": 0,
            "label": false
        },
        {
            "id": 15,
            "name": "pet_식품용기류_불투명_병류_대_수평압축_라벨유",
            "category_id": 1,
            "container": true,
            "transparent": false,
            "shape": 0,
            "size": 0,
            "compress": 1,
            "label": true
        },
        {
            "id": 16,
            "name": "pet_식품용기류_불투명_병류_대_수평압축_라벨무",
            "category_id": 1,
            "container": true,
            "transparent": false,
            "shape": 0,
            "size": 0,
            "compress": 1,
            "label": false
        },
        {
            "id": 17,
            "name": "pet_식품용기류_불투명_병류_대_수직압축_라벨유",
            "category_id": 1,
            "container": true,
            "transparent": false,
            "shape": 0,
            "size": 0,
            "compress": 2,
            "label": true
        },
        {
            "id": 18,
            "name": "pet_식품용기류_불투명_병류_대_수직압축_라벨무",
            "category_id": 1,
            "container": true,
            "transparent": false,
            "shape": 0,
            "size": 0,
            "compress": 2,
            "label": false
        },
        {
            "id": 19,
            "name": "pet_식품용기류_불투명_병류_소_비압축_라벨유",
            "category_id": 1,
            "container": true,
            "transparent": false,
            "shape": 0,
            "size": 1,
            "compress": 0,
            "label": true
        },
        {
            "id": 20,
            "name": "pet_식품용기류_불투명_병류_소_비압축_라벨무",
            "category_id": 1,
            "container": true,
            "transparent": false,
            "shape": 0,
            "size": 1,
            "compress": 0,
            "label": false
        },
        {
            "id": 21,
            "name": "pet_식품용기류_불투명_병류_소_수평압축_라벨유",
            "category_id": 1,
            "container": true,
            "transparent": false,
            "shape": 0,
            "size": 1,
            "compress": 1,
            "label": true
        },
        {
            "id": 22,
            "name": "pet_식품용기류_불투명_병류_소_수평압축_라벨무",
            "category_id": 1,
            "container": true,
            "transparent": false,
            "shape": 0,
            "size": 1,
            "compress": 1,
            "label": false
        },
        {
            "id": 23,
            "name": "pet_식품용기류_불투명_병류_소_수직압축_라벨유",
            "category_id": 1,
            "container": true,
            "transparent": false,
            "shape": 0,
            "size": 1,
            "compress": 2,
            "label": true
        },
        {
            "id": 24,
            "name": "pet_식품용기류_불투명_병류_소_수직압축_라벨무",
            "category_id": 1,
            "container": true,
            "transparent": false,
            "shape": 0,
            "size": 1,
            "compress": 2,
            "label": false
        },
        {
            "id": 25,
            "name": "pet_식품용기류_투명_기타_대_비압축_라벨무",
            "category_id": 1,
            "container": true,
            "transparent": true,
            "shape": 3,
            "size": 0,
            "compress": 0,
            "label": false
        },
        {
            "id": 26,
            "name": "pet_식품용기류_투명_기타_대_수평압축_라벨무",
            "category_id": 1,
            "container": true,
            "transparent": true,
            "shape": 3,
            "size": 0,
            "compress": 1,
            "label": false
        },
        {
            "id": 27,
            "name": "pet_식품용기류_투명_기타_대_수직압축_라벨무",
            "category_id": 1,
            "container": true,
            "transparent": true,
            "shape": 3,
            "size": 0,
            "compress": 2,
            "label": false
        },
        {
            "id": 28,
            "name": "pet_식품용기류_투명_기타_소_비압축_라벨무",
            "category_id": 1,
            "container": true,
            "transparent": true,
            "shape": 3,
            "size": 1,
            "compress": 0,
            "label": false
        },
        {
            "id": 29,
            "name": "pet_식품용기류_투명_기타_소_수평압축_라벨무",
            "category_id": 1,
            "container": true,
            "transparent": true,
            "shape": 3,
            "size": 1,
            "compress": 1,
            "label": false
        },
        {
            "id": 30,
            "name": "pet_식품용기류_투명_기타_소_수직압축_라벨무",
            "category_id": 1,
            "container": true,
            "transparent": true,
            "shape": 3,
            "size": 1,
            "compress": 2,
            "label": false
        },
        {
            "id": 31,
            "name": "ps_식품용기류_불투명_기타_대_비압축_라벨무",
            "category_id": 2,
            "container": true,
            "transparent": false,
            "shape": 3,
            "size": 0,
            "compress": 0,
            "label": false
        },
        {
            "id": 32,
            "name": "ps_식품용기류_불투명_기타_대_수평압축_라벨무",
            "category_id": 2,
            "container": true,
            "transparent": false,
            "shape": 3,
            "size": 0,
            "compress": 1,
            "label": false
        },
        {
            "id": 33,
            "name": "ps_식품용기류_불투명_기타_대_수직압축_라벨무",
            "category_id": 2,
            "container": true,
            "transparent": false,
            "shape": 3,
            "size": 0,
            "compress": 2,
            "label": false
        },
        {
            "id": 34,
            "name": "ps_식품용기류_불투명_기타_소_비압축_라벨무",
            "category_id": 2,
            "container": true,
            "transparent": false,
            "shape": 3,
            "size": 1,
            "compress": 0,
            "label": false
        },
        {
            "id": 35,
            "name": "ps_식품용기류_불투명_기타_소_수평압축_라벨무",
            "category_id": 2,
            "container": true,
            "transparent": false,
            "shape": 3,
            "size": 1,
            "compress": 1,
            "label": false
        },
        {
            "id": 36,
            "name": "ps_식품용기류_불투명_기타_소_수직압축_라벨무",
            "category_id": 2,
            "container": true,
            "transparent": false,
            "shape": 3,
            "size": 1,
            "compress": 2,
            "label": false
        },
        {
            "id": 37,
            "name": "ps_식품용기류_불투명_병류_소_비압축_라벨유",
            "category_id": 2,
            "container": true,
            "transparent": false,
            "shape": 0,
            "size": 1,
            "compress": 0,
            "label": true
        },
        {
            "id": 38,
            "name": "ps_식품용기류_불투명_병류_소_비압축_라벨무",
            "category_id": 2,
            "container": true,
            "transparent": false,
            "shape": 0,
            "size": 1,
            "compress": 0,
            "label": false
        },
        {
            "id": 39,
            "name": "ps_식품용기류_불투명_병류_소_수평압축_라벨유",
            "category_id": 2,
            "container": true,
            "transparent": false,
            "shape": 0,
            "size": 1,
            "compress": 1,
            "label": true
        },
        {
            "id": 40,
            "name": "ps_식품용기류_불투명_병류_소_수평압축_라벨무",
            "category_id": 2,
            "container": true,
            "transparent": false,
            "shape": 0,
            "size": 1,
            "compress": 1,
            "label": false
        },
        {
            "id": 41,
            "name": "ps_식품용기류_불투명_병류_소_수직압축_라벨유",
            "category_id": 2,
            "container": true,
            "transparent": false,
            "shape": 0,
            "size": 1,
            "compress": 2,
            "label": true
        },
        {
            "id": 42,
            "name": "ps_식품용기류_불투명_병류_소_수직압축_라벨무",
            "category_id": 2,
            "container": true,
            "transparent": false,
            "shape": 0,
            "size": 1,
            "compress": 2,
            "label": false
        },
        {
            "id": 44,
            "name": "pp_식품용기류_불투명_원형_대_비압축_라벨무",
            "category_id": 3,
            "container": true,
            "transparent": false,
            "shape": 1,
            "size": 0,
            "compress": 0,
            "label": false
        },
        {
            "id": 46,
            "name": "pp_식품용기류_불투명_원형_대_수평압축_라벨무",
            "category_id": 3,
            "container": true,
            "transparent": false,
            "shape": 1,
            "size": 0,
            "compress": 1,
            "label": false
        },
        {
            "id": 48,
            "name": "pp_식품용기류_불투명_원형_대_수직압축_라벨무",
            "category_id": 3,
            "container": true,
            "transparent": false,
            "shape": 1,
            "size": 0,
            "compress": 2,
            "label": false
        },
        {
            "id": 50,
            "name": "pp_식품용기류_불투명_원형_소_비압축_라벨무",
            "category_id": 3,
            "container": true,
            "transparent": false,
            "shape": 1,
            "size": 1,
            "compress": 0,
            "label": false
        },
        {
            "id": 52,
            "name": "pp_식품용기류_불투명_원형_소_수평압축_라벨무",
            "category_id": 3,
            "container": true,
            "transparent": false,
            "shape": 1,
            "size": 1,
            "compress": 1,
            "label": false
        },
        {
            "id": 54,
            "name": "pp_식품용기류_불투명_원형_소_수직압축_라벨무",
            "category_id": 3,
            "container": true,
            "transparent": false,
            "shape": 1,
            "size": 1,
            "compress": 2,
            "label": false
        },
        {
            "id": 55,
            "name": "pp_식품용기류_불투명_사각형_대_비압축_라벨유",
            "category_id": 3,
            "container": true,
            "transparent": false,
            "shape": 2,
            "size": 0,
            "compress": 0,
            "label": true
        },
        {
            "id": 56,
            "name": "pp_식품용기류_불투명_사각형_대_비압축_라벨무",
            "category_id": 3,
            "container": true,
            "transparent": false,
            "shape": 2,
            "size": 0,
            "compress": 0,
            "label": false
        },
        {
            "id": 57,
            "name": "pp_식품용기류_불투명_사각형_대_수평압축_라벨유",
            "category_id": 3,
            "container": true,
            "transparent": false,
            "shape": 2,
            "size": 0,
            "compress": 1,
            "label": true
        },
        {
            "id": 58,
            "name": "pp_식품용기류_불투명_사각형_대_수평압축_라벨무",
            "category_id": 3,
            "container": true,
            "transparent": false,
            "shape": 2,
            "size": 0,
            "compress": 1,
            "label": false
        },
        {
            "id": 59,
            "name": "pp_식품용기류_불투명_사각형_대_수직압축_라벨유",
            "category_id": 3,
            "container": true,
            "transparent": false,
            "shape": 2,
            "size": 0,
            "compress": 2,
            "label": true
        },
        {
            "id": 60,
            "name": "pp_식품용기류_불투명_사각형_대_수직압축_라벨무",
            "category_id": 3,
            "container": true,
            "transparent": false,
            "shape": 2,
            "size": 0,
            "compress": 2,
            "label": false
        },
        {
            "id": 61,
            "name": "pp_식품용기류_불투명_사각형_소_비압축_라벨유",
            "category_id": 3,
            "container": true,
            "transparent": false,
            "shape": 2,
            "size": 1,
            "compress": 0,
            "label": true
        },
        {
            "id": 62,
            "name": "pp_식품용기류_불투명_사각형_소_비압축_라벨무",
            "category_id": 3,
            "container": true,
            "transparent": false,
            "shape": 2,
            "size": 1,
            "compress": 0,
            "label": false
        },
        {
            "id": 63,
            "name": "pp_식품용기류_불투명_사각형_소_수평압축_라벨유",
            "category_id": 3,
            "container": true,
            "transparent": false,
            "shape": 2,
            "size": 1,
            "compress": 1,
            "label": true
        },
        {
            "id": 64,
            "name": "pp_식품용기류_불투명_사각형_소_수평압축_라벨무",
            "category_id": 3,
            "container": true,
            "transparent": false,
            "shape": 2,
            "size": 1,
            "compress": 1,
            "label": false
        },
        {
            "id": 65,
            "name": "pp_식품용기류_불투명_사각형_소_수직압축_라벨유",
            "category_id": 3,
            "container": true,
            "transparent": false,
            "shape": 2,
            "size": 1,
            "compress": 2,
            "label": true
        },
        {
            "id": 66,
            "name": "pp_식품용기류_불투명_사각형_소_수직압축_라벨무",
            "category_id": 3,
            "container": true,
            "transparent": false,
            "shape": 2,
            "size": 1,
            "compress": 2,
            "label": false
        },
        {
            "id": 67,
            "name": "pp_기타_불투명_기타_기타_비압축_라벨무",
            "category_id": 3,
            "container": false,
            "transparent": false,
            "shape": 3,
            "size": 2,
            "compress": 0,
            "label": false
        },
        {
            "id": 68,
            "name": "pe_식품용기류_불투명_원형_대_비압축_라벨유",
            "category_id": 4,
            "container": true,
            "transparent": false,
            "shape": 1,
            "size": 0,
            "compress": 0,
            "label": true
        },
        {
            "id": 69,
            "name": "pe_식품용기류_불투명_원형_대_비압축_라벨무",
            "category_id": 4,
            "container": true,
            "transparent": false,
            "shape": 1,
            "size": 0,
            "compress": 0,
            "label": false
        },
        {
            "id": 70,
            "name": "pe_식품용기류_불투명_원형_대_수평압축_라벨유",
            "category_id": 4,
            "container": true,
            "transparent": false,
            "shape": 1,
            "size": 0,
            "compress": 1,
            "label": true
        },
        {
            "id": 71,
            "name": "pe_식품용기류_불투명_원형_대_수평압축_라벨무",
            "category_id": 4,
            "container": true,
            "transparent": false,
            "shape": 1,
            "size": 0,
            "compress": 1,
            "label": false
        },
        {
            "id": 72,
            "name": "pe_식품용기류_불투명_원형_대_수직압축_라벨유",
            "category_id": 4,
            "container": true,
            "transparent": false,
            "shape": 1,
            "size": 0,
            "compress": 2,
            "label": true
        },
        {
            "id": 73,
            "name": "pe_식품용기류_불투명_원형_대_수직압축_라벨무",
            "category_id": 4,
            "container": true,
            "transparent": false,
            "shape": 1,
            "size": 0,
            "compress": 2,
            "label": false
        },
        {
            "id": 74,
            "name": "pe_식품용기류_불투명_원형_소_비압축_라벨유",
            "category_id": 4,
            "container": true,
            "transparent": false,
            "shape": 1,
            "size": 1,
            "compress": 0,
            "label": true
        },
        {
            "id": 75,
            "name": "pe_식품용기류_불투명_원형_소_비압축_라벨무",
            "category_id": 4,
            "container": true,
            "transparent": false,
            "shape": 1,
            "size": 1,
            "compress": 0,
            "label": false
        },
        {
            "id": 76,
            "name": "pe_식품용기류_불투명_원형_소_수평압축_라벨유",
            "category_id": 4,
            "container": true,
            "transparent": false,
            "shape": 1,
            "size": 1,
            "compress": 1,
            "label": true
        },
        {
            "id": 77,
            "name": "pe_식품용기류_불투명_원형_소_수평압축_라벨무",
            "category_id": 4,
            "container": true,
            "transparent": false,
            "shape": 1,
            "size": 1,
            "compress": 1,
            "label": false
        },
        {
            "id": 78,
            "name": "pe_식품용기류_불투명_원형_소_수직압축_라벨유",
            "category_id": 4,
            "container": true,
            "transparent": false,
            "shape": 1,
            "size": 1,
            "compress": 2,
            "label": true
        },
        {
            "id": 79,
            "name": "pe_식품용기류_불투명_원형_소_수직압축_라벨무",
            "category_id": 4,
            "container": true,
            "transparent": false,
            "shape": 1,
            "size": 1,
            "compress": 2,
            "label": false
        },
        {
            "id": 80,
            "name": "pe_식품용기류_불투명_사각형_대_비압축_라벨유",
            "category_id": 4,
            "container": true,
            "transparent": false,
            "shape": 2,
            "size": 0,
            "compress": 0,
            "label": true
        },
        {
            "id": 81,
            "name": "pe_식품용기류_불투명_사각형_대_비압축_라벨무",
            "category_id": 4,
            "container": true,
            "transparent": false,
            "shape": 2,
            "size": 0,
            "compress": 0,
            "label": false
        },
        {
            "id": 82,
            "name": "pe_식품용기류_불투명_사각형_대_수평압축_라벨유",
            "category_id": 4,
            "container": true,
            "transparent": false,
            "shape": 2,
            "size": 0,
            "compress": 1,
            "label": true
        },
        {
            "id": 83,
            "name": "pe_식품용기류_불투명_사각형_대_수평압축_라벨무",
            "category_id": 4,
            "container": true,
            "transparent": false,
            "shape": 2,
            "size": 0,
            "compress": 1,
            "label": false
        },
        {
            "id": 84,
            "name": "pe_식품용기류_불투명_사각형_대_수직압축_라벨유",
            "category_id": 4,
            "container": true,
            "transparent": false,
            "shape": 2,
            "size": 0,
            "compress": 2,
            "label": true
        },
        {
            "id": 85,
            "name": "pe_식품용기류_불투명_사각형_대_수직압축_라벨무",
            "category_id": 4,
            "container": true,
            "transparent": false,
            "shape": 2,
            "size": 0,
            "compress": 2,
            "label": false
        },
        {
            "id": 86,
            "name": "pe_식품용기류_불투명_사각형_소_비압축_라벨유",
            "category_id": 4,
            "container": true,
            "transparent": false,
            "shape": 2,
            "size": 1,
            "compress": 0,
            "label": true
        },
        {
            "id": 87,
            "name": "pe_식품용기류_불투명_사각형_소_비압축_라벨무",
            "category_id": 4,
            "container": true,
            "transparent": false,
            "shape": 2,
            "size": 1,
            "compress": 0,
            "label": false
        },
        {
            "id": 88,
            "name": "pe_식품용기류_불투명_사각형_소_수평압축_라벨유",
            "category_id": 4,
            "container": true,
            "transparent": false,
            "shape": 2,
            "size": 1,
            "compress": 1,
            "label": true
        },
        {
            "id": 89,
            "name": "pe_식품용기류_불투명_사각형_소_수평압축_라벨무",
            "category_id": 4,
            "container": true,
            "transparent": false,
            "shape": 2,
            "size": 1,
            "compress": 1,
            "label": false
        },
        {
            "id": 90,
            "name": "pe_식품용기류_불투명_사각형_소_수직압축_라벨유",
            "category_id": 4,
            "container": true,
            "transparent": false,
            "shape": 2,
            "size": 1,
            "compress": 2,
            "label": true
        },
        {
            "id": 91,
            "name": "pe_식품용기류_불투명_사각형_소_수직압축_라벨무",
            "category_id": 4,
            "container": true,
            "transparent": false,
            "shape": 2,
            "size": 1,
            "compress": 2,
            "label": false
        },
        {
            "id": 92,
            "name": "pe_기타_불투명_기타_대_비압축_라벨유",
            "category_id": 4,
            "container": false,
            "transparent": false,
            "shape": 3,
            "size": 0,
            "compress": 0,
            "label": true
        },
        {
            "id": 93,
            "name": "pe_기타_불투명_기타_대_비압축_라벨무",
            "category_id": 4,
            "container": false,
            "transparent": false,
            "shape": 3,
            "size": 0,
            "compress": 0,
            "label": false
        },
        {
            "id": 94,
            "name": "pe_기타_불투명_기타_대_수평압축_라벨유",
            "category_id": 4,
            "container": false,
            "transparent": false,
            "shape": 3,
            "size": 0,
            "compress": 1,
            "label": true
        },
        {
            "id": 95,
            "name": "pe_기타_불투명_기타_대_수평압축_라벨무",
            "category_id": 4,
            "container": false,
            "transparent": false,
            "shape": 3,
            "size": 0,
            "compress": 1,
            "label": false
        },
        {
            "id": 96,
            "name": "pe_기타_불투명_기타_대_수직압축_라벨유",
            "category_id": 4,
            "container": false,
            "transparent": false,
            "shape": 3,
            "size": 0,
            "compress": 2,
            "label": true
        },
        {
            "id": 97,
            "name": "pe_기타_불투명_기타_대_수직압축_라벨무",
            "category_id": 4,
            "container": false,
            "transparent": false,
            "shape": 3,
            "size": 0,
            "compress": 2,
            "label": false
        },
        {
            "id": 98,
            "name": "pe_기타_불투명_기타_소_비압축_라벨유",
            "category_id": 4,
            "container": false,
            "transparent": false,
            "shape": 3,
            "size": 1,
            "compress": 0,
            "label": true
        },
        {
            "id": 99,
            "name": "pe_기타_불투명_기타_소_비압축_라벨무",
            "category_id": 4,
            "container": false,
            "transparent": false,
            "shape": 3,
            "size": 1,
            "compress": 0,
            "label": false
        },
        {
            "id": 100,
            "name": "pe_기타_불투명_기타_소_수평압축_라벨유",
            "category_id": 4,
            "container": false,
            "transparent": false,
            "shape": 3,
            "size": 1,
            "compress": 1,
            "label": true
        },
        {
            "id": 101,
            "name": "pe_기타_불투명_기타_소_수평압축_라벨무",
            "category_id": 4,
            "container": false,
            "transparent": false,
            "shape": 3,
            "size": 1,
            "compress": 1,
            "label": false
        },
        {
            "id": 102,
            "name": "pe_기타_불투명_기타_소_수직압축_라벨유",
            "category_id": 4,
            "container": false,
            "transparent": false,
            "shape": 3,
            "size": 1,
            "compress": 2,
            "label": true
        },
        {
            "id": 103,
            "name": "pe_기타_불투명_기타_소_수직압축_라벨무",
            "category_id": 4,
            "container": false,
            "transparent": false,
            "shape": 3,
            "size": 1,
            "compress": 2,
            "label": false
        }
    ]
}